MANIFEST.in
setup.py
django_fresh_media.egg-info/PKG-INFO
django_fresh_media.egg-info/SOURCES.txt
django_fresh_media.egg-info/dependency_links.txt
django_fresh_media.egg-info/not-zip-safe
django_fresh_media.egg-info/requires.txt
django_fresh_media.egg-info/top_level.txt
fresh_media/__init__.py
fresh_media/hash_methods.py
fresh_media/templatetags/__init__.py
fresh_media/templatetags/freshmedia.py