Metadata-Version: 1.0
Name: django-fresh-media
Version: 0.61
Summary: Application to add hashes to media files
Home-page: https://bitbucket.org/djangostars/django-fresh-media
Author: Roman Osipenko
Author-email: roman.osipenko@djangostars.com
License: BSD
Keywords: django media hash browser
Platform: any
Classifier: Environment :: Web Environment
Classifier: Framework :: Django
Classifier: Intended Audience :: Developers
Classifier: License :: OSI Approved :: BSD License
Classifier: Operating System :: OS Independent
Classifier: Programming Language :: Python
Classifier: Topic :: Internet :: WWW/HTTP :: Dynamic Content
Classifier: Topic :: Software Development :: Libraries :: Python Modules
